document_cleaner.py
ingest.py
ingest_cli-1.0.2.dist-info/licenses/LICENSE
ingest_cli-1.0.2.dist-info/METADATA
ingest_cli-1.0.2.dist-info/WHEEL
ingest_cli-1.0.2.dist-info/entry_points.txt
ingest_cli-1.0.2.dist-info/top_level.txt
ingest_cli-1.0.2.dist-info/RECORD
