Metadata-Version: 2.4
Name: ingest-cli
Version: 1.0.2
Summary: High-quality document processing for RAG pipelines, supporting multiple formats and processing backends
Home-page: https://github.com/therealtimex/ingest
Author: RealTimeX
Author-email: RealTimeX <trung@realtimex.ai>
License: MIT
Project-URL: Homepage, https://github.com/therealtimex/ingest
Project-URL: Repository, https://github.com/therealtimex/ingest
Project-URL: Issues, https://github.com/therealtimex/ingest/issues
Keywords: pdf,document-processing,ocr,nlp,rag,ingest,llm,table-extraction,vector-database
Classifier: Development Status :: 4 - Beta
Classifier: Intended Audience :: Developers
Classifier: Topic :: Scientific/Engineering :: Artificial Intelligence
Classifier: Topic :: Text Processing :: Markup :: Markdown
Classifier: License :: OSI Approved :: MIT License
Classifier: Programming Language :: Python :: 3
Classifier: Programming Language :: Python :: 3.10
Classifier: Programming Language :: Python :: 3.11
Classifier: Programming Language :: Python :: 3.12
Requires-Python: >=3.10
License-File: LICENSE
Requires-Dist: loguru>=0.7.0
Requires-Dist: tqdm>=4.65.0
Requires-Dist: pypdf>=3.0.0
Requires-Dist: python-docx>=1.0.0
Requires-Dist: openpyxl>=3.1.0
Requires-Dist: Pillow>=10.0.0
Provides-Extra: marker
Requires-Dist: marker-pdf[full]>=0.2.0; extra == "marker"
Provides-Extra: llm
Requires-Dist: google-generativeai; extra == "llm"
Requires-Dist: anthropic; extra == "llm"
Requires-Dist: openai; extra == "llm"
Provides-Extra: full
Requires-Dist: marker-pdf[full]>=0.2.0; extra == "full"
Requires-Dist: google-generativeai; extra == "full"
Requires-Dist: anthropic; extra == "full"
Requires-Dist: openai; extra == "full"
Provides-Extra: dev
Requires-Dist: pytest>=7.0.0; extra == "dev"
Requires-Dist: black>=23.0.0; extra == "dev"
Requires-Dist: ruff>=0.1.0; extra == "dev"
Dynamic: author
Dynamic: home-page
Dynamic: license-file
Dynamic: requires-python
